checkprimenumbers/__init__.py
checkprimenumbers/prime.py
checkprimenumbers-0.0.1.dist-info/METADATA
checkprimenumbers-0.0.1.dist-info/WHEEL
checkprimenumbers-0.0.1.dist-info/top_level.txt
checkprimenumbers-0.0.1.dist-info/RECORD
